spseg/__init__.py
spseg/so/cythonsp.cpython-36m-x86_64-linux-gnu.so
spseg/so/cythonsp.cpython-37m-x86_64-linux-gnu.so
spseg/so/cythonsp.so
spseg-1.0.8.data/data/LICENSE
spseg-1.0.8.data/data/MANIFEST.in
spseg-1.0.8.data/data/README.md
spseg-1.0.8.dist-info/LICENSE
spseg-1.0.8.dist-info/METADATA
spseg-1.0.8.dist-info/WHEEL
spseg-1.0.8.dist-info/top_level.txt
spseg-1.0.8.dist-info/RECORD
