Metadata-Version: 2.1
Name: spseg
Version: 1.0.8
Summary: A segmentation and postagging tool package
Home-page: UNKNOWN
Author: xuwenqiang
Author-email: xuwenqiang0563@163.com
License: MIT
Platform: UNKNOWN
